<?xml version="1.0" encoding="UTF-8" standalone="yes"?>
<OfficeApp xmlns="http://schemas.microsoft.com/office/appforoffice/1.1"
  xmlns:xsi="http://www.w3.org/2001/XMLSchema-instance"
  xmlns:bt="http://schemas.microsoft.com/office/officeappbasictypes/1.0"
  xmlns:ov="http://schemas.microsoft.com/office/taskpaneappversionoverrides" xsi:type="TaskPaneApp">
  <Id>fc1ceb91-f7ef-451f-9300-92069a9aecad</Id>
  <Version>1.0.0.1</Version>
  <ProviderName>Local</ProviderName>
  <DefaultLocale>en-US</DefaultLocale>
  <DisplayName DefaultValue="Local Demo AddIn"/>
  <Description DefaultValue="A simple hello world Office Add-in."/>
  <IconUrl DefaultValue="https://localhost:5000/vite.png"/>
  <HighResolutionIconUrl DefaultValue="https://localhost:5000/vite.png"/>
  <SupportUrl DefaultValue="https://localhost:5000/learn"/>
  <AppDomains>
    <AppDomain>https://localhost:5000/</AppDomain>
  </AppDomains>
  <Hosts>
    <Host Name="Document"/>
  </Hosts>
  <DefaultSettings>
    <SourceLocation DefaultValue="https://localhost:5000/index.html"/>
  </DefaultSettings>
  <Permissions>ReadWriteDocument</Permissions>
  <VersionOverrides xmlns="http://schemas.microsoft.com/office/taskpaneappversionoverrides" xsi:type="VersionOverridesV1_0">
    <Hosts>
      <Host xsi:type="Document">
      </Host>
    </Hosts>
    <Resources>
      <bt:Urls>
        <bt:Url id="GetStarted.LearnMoreUrl" DefaultValue="http://go.microsoft.com/fwlink/?LinkId=276812"/>
        <bt:Url id="Taskpane.Url" DefaultValue="https://localhost:5000/index.html"/>
      </bt:Urls>
    </Resources>
  </VersionOverrides>
</OfficeApp>